[
  {
    "name": "404",
    "path": "*",
    "component": "C:\\\\Users\\\\dinhp\\\\Desktop\\\\New folder (8)\\\\Client\\\\pages\\\\404.vue",
    "chunkName": "pages/404.vue"
  },
  {
    "name": "home-page",
    "path": "/",
    "component": "C:\\\\Users\\\\dinhp\\\\Desktop\\\\New folder (8)\\\\Client\\\\pages\\\\index.vue",
    "chunkName": "pages/index.vue"
  },
  {
    "name": "shop-by-brand",
    "path": "/thuong-hieu/:slug",
    "component": "C:\\\\Users\\\\dinhp\\\\Desktop\\\\New folder (8)\\\\Client\\\\pages\\\\product\\\\brand.vue",
    "chunkName": "pages/product/brand.vue"
  },
  {
    "name": "shop-by-category",
    "path": "/danh-muc/:slug",
    "component": "C:\\\\Users\\\\dinhp\\\\Desktop\\\\New folder (8)\\\\Client\\\\pages\\\\product\\\\index.vue",
    "chunkName": "pages/product/index.vue"
  },
  {
    "name": "search-page",
    "path": "/search",
    "component": "C:\\\\Users\\\\dinhp\\\\Desktop\\\\New folder (8)\\\\Client\\\\pages\\\\product\\\\search.vue",
    "chunkName": "pages/product/search.vue"
  },
  {
    "name": "product-detail",
    "path": "/san-pham/:slug",
    "component": "C:\\\\Users\\\\dinhp\\\\Desktop\\\\New folder (8)\\\\Client\\\\pages\\\\product\\\\_slug.vue",
    "chunkName": "pages/product/_slug.vue"
  },
  {
    "name": "cart",
    "path": "/gio-hang",
    "component": "C:\\\\Users\\\\dinhp\\\\Desktop\\\\New folder (8)\\\\Client\\\\pages\\\\cart.vue",
    "chunkName": "pages/cart.vue"
  },
  {
    "name": "checkout",
    "path": "/thanh-toan",
    "component": "C:\\\\Users\\\\dinhp\\\\Desktop\\\\New folder (8)\\\\Client\\\\pages\\\\checkout.vue",
    "chunkName": "pages/checkout.vue"
  },
  {
    "name": "contact",
    "path": "/lien-he",
    "component": "C:\\\\Users\\\\dinhp\\\\Desktop\\\\New folder (8)\\\\Client\\\\pages\\\\contact.vue",
    "chunkName": "pages/contact.vue"
  },
  {
    "name": "about",
    "path": "/gioi-thieu",
    "component": "C:\\\\Users\\\\dinhp\\\\Desktop\\\\New folder (8)\\\\Client\\\\pages\\\\about.vue",
    "chunkName": "pages/about.vue"
  },
  {
    "name": "thanks",
    "path": "/thanh-cong",
    "component": "C:\\\\Users\\\\dinhp\\\\Desktop\\\\New folder (8)\\\\Client\\\\pages\\\\thanks.vue",
    "chunkName": "pages/thanks.vue"
  },
  {
    "name": "login",
    "path": "/dang-nhap",
    "component": "C:\\\\Users\\\\dinhp\\\\Desktop\\\\New folder (8)\\\\Client\\\\pages\\\\login.vue",
    "chunkName": "pages/login.vue"
  },
  {
    "name": "register",
    "path": "/dang-ky",
    "component": "C:\\\\Users\\\\dinhp\\\\Desktop\\\\New folder (8)\\\\Client\\\\pages\\\\register.vue",
    "chunkName": "pages/register.vue"
  },
  {
    "name": "forgot-password",
    "path": "/quen-mat-khau",
    "component": "C:\\\\Users\\\\dinhp\\\\Desktop\\\\New folder (8)\\\\Client\\\\pages\\\\forgot.vue",
    "chunkName": "pages/forgot.vue"
  },
  {
    "name": "reset-pasword",
    "path": "/reset-password",
    "component": "C:\\\\Users\\\\dinhp\\\\Desktop\\\\New folder (8)\\\\Client\\\\pages\\\\resetPassword.vue",
    "chunkName": "pages/resetPassword.vue"
  },
  {
    "name": "verify",
    "path": "/verify-email",
    "component": "C:\\\\Users\\\\dinhp\\\\Desktop\\\\New folder (8)\\\\Client\\\\pages\\\\verify.vue",
    "chunkName": "pages/verify.vue"
  },
  {
    "name": "blog",
    "path": "/loai-tin/:slug",
    "component": "C:\\\\Users\\\\dinhp\\\\Desktop\\\\New folder (8)\\\\Client\\\\pages\\\\blog\\\\blog.vue",
    "chunkName": "pages/blog/blog.vue"
  },
  {
    "name": "blog-detail",
    "path": "/tin-tuc/:slug",
    "component": "C:\\\\Users\\\\dinhp\\\\Desktop\\\\New folder (8)\\\\Client\\\\pages\\\\blog\\\\_slug.vue",
    "chunkName": "pages/blog/_slug.vue"
  },
  {
    "path": "/profile",
    "component": "C:\\\\Users\\\\dinhp\\\\Desktop\\\\New folder (8)\\\\Client\\\\pages\\\\user\\\\index.vue",
    "chunkName": "pages/user/profile.vue",
    "children": [
      {
        "path": "",
        "component": "pages/user/userInfo.vue.vue",
        "name": "user-info"
      },
      {
        "path": "change-password",
        "component": "pages/user/changePassword.vue",
        "name": "change-password"
      }
    ]
  }
]
